{
    "asset": {
        "format": "png",
        "id": "0ebf2f9b09c45b25e6fea0780d7e18a9",
        "name": "1651966739.734102.png",
        "path": "file:E:/Robocup/robocup/ml_data/victims/victims/1651966739.734102.png",
        "size": {
            "width": 160,
            "height": 120
        },
        "state": 2,
        "type": 1
    },
    "regions": [
        {
            "id": "Ep1WP4RFM",
            "type": "RECTANGLE",
            "tags": [
                "dead"
            ],
            "boundingBox": {
                "height": 18.7012987012987,
                "width": 17.27272727272727,
                "left": 87.46753246753246,
                "top": 18.7012987012987
            },
            "points": [
                {
                    "x": 87.46753246753246,
                    "y": 18.7012987012987
                },
                {
                    "x": 104.74025974025973,
                    "y": 18.7012987012987
                },
                {
                    "x": 104.74025974025973,
                    "y": 37.4025974025974
                },
                {
                    "x": 87.46753246753246,
                    "y": 37.4025974025974
                }
            ]
        }
    ],
    "version": "2.2.0"
}