{
    "asset": {
        "format": "png",
        "id": "11d2d281978c8d05d7487045d2206c17",
        "name": "1651948036.21.png",
        "path": "file:E:/Robocup/robocup/ml_data/victims/victims/1651948036.21.png",
        "size": {
            "width": 160,
            "height": 120
        },
        "state": 2,
        "type": 1
    },
    "regions": [
        {
            "id": "wzUZ2O176",
            "type": "RECTANGLE",
            "tags": [
                "living"
            ],
            "boundingBox": {
                "height": 18.57142857142857,
                "width": 17.532467532467532,
                "left": 99.15584415584415,
                "top": 15.454545454545453
            },
            "points": [
                {
                    "x": 99.15584415584415,
                    "y": 15.454545454545453
                },
                {
                    "x": 116.68831168831167,
                    "y": 15.454545454545453
                },
                {
                    "x": 116.68831168831167,
                    "y": 34.02597402597402
                },
                {
                    "x": 99.15584415584415,
                    "y": 34.02597402597402
                }
            ]
        }
    ],
    "version": "2.2.0"
}