{
    "asset": {
        "format": "png",
        "id": "391f06ad9efefe89e10e02a3ef71e65d",
        "name": "1651960242.3786488.png",
        "path": "file:E:/Robocup/robocup/ml_data/victims/victims/1651960242.3786488.png",
        "size": {
            "width": 160,
            "height": 120
        },
        "state": 2,
        "type": 1
    },
    "regions": [
        {
            "id": "vk2RhU0QR",
            "type": "RECTANGLE",
            "tags": [
                "living"
            ],
            "boundingBox": {
                "height": 28.57142857142857,
                "width": 28.701298701298697,
                "left": 102.66233766233765,
                "top": 45.19480519480519
            },
            "points": [
                {
                    "x": 102.66233766233765,
                    "y": 45.19480519480519
                },
                {
                    "x": 131.36363636363635,
                    "y": 45.19480519480519
                },
                {
                    "x": 131.36363636363635,
                    "y": 73.76623376623375
                },
                {
                    "x": 102.66233766233765,
                    "y": 73.76623376623375
                }
            ]
        }
    ],
    "version": "2.2.0"
}