{
    "asset": {
        "format": "png",
        "id": "9ad74dfad53000762d6117dbe0ab053b",
        "name": "1651948005.53.png",
        "path": "file:E:/Robocup/robocup/ml_data/victims/victims/1651948005.53.png",
        "size": {
            "width": 160,
            "height": 120
        },
        "state": 2,
        "type": 1
    },
    "regions": [
        {
            "id": "zHlJ0v95O",
            "type": "RECTANGLE",
            "tags": [
                "dead"
            ],
            "boundingBox": {
                "height": 21.558441558441558,
                "width": 21.16883116883117,
                "left": 114.99999999999999,
                "top": 27.53246753246753
            },
            "points": [
                {
                    "x": 114.99999999999999,
                    "y": 27.53246753246753
                },
                {
                    "x": 136.16883116883116,
                    "y": 27.53246753246753
                },
                {
                    "x": 136.16883116883116,
                    "y": 49.090909090909086
                },
                {
                    "x": 114.99999999999999,
                    "y": 49.090909090909086
                }
            ]
        }
    ],
    "version": "2.2.0"
}