{
    "asset": {
        "format": "png",
        "id": "a55fb0a7af635e02c46e186e68929307",
        "name": "1651960319.3943706.png",
        "path": "file:E:/Robocup/robocup/ml_data/victims/victims/1651960319.3943706.png",
        "size": {
            "width": 160,
            "height": 120
        },
        "state": 2,
        "type": 1
    },
    "regions": [
        {
            "id": "LAoncmzB9",
            "type": "RECTANGLE",
            "tags": [
                "living"
            ],
            "boundingBox": {
                "height": 18.051948051948045,
                "width": 19.025974025974023,
                "left": 47.077922077922075,
                "top": 19.999999999999993
            },
            "points": [
                {
                    "x": 47.077922077922075,
                    "y": 19.999999999999993
                },
                {
                    "x": 66.10389610389609,
                    "y": 19.999999999999993
                },
                {
                    "x": 66.10389610389609,
                    "y": 38.05194805194804
                },
                {
                    "x": 47.077922077922075,
                    "y": 38.05194805194804
                }
            ]
        },
        {
            "id": "-O28UrvQN",
            "type": "RECTANGLE",
            "tags": [
                "dead"
            ],
            "boundingBox": {
                "height": 13.896103896103895,
                "width": 14.285714285714285,
                "left": 79.02597402597402,
                "top": 9.610389610389609
            },
            "points": [
                {
                    "x": 79.02597402597402,
                    "y": 9.610389610389609
                },
                {
                    "x": 93.3116883116883,
                    "y": 9.610389610389609
                },
                {
                    "x": 93.3116883116883,
                    "y": 23.506493506493506
                },
                {
                    "x": 79.02597402597402,
                    "y": 23.506493506493506
                }
            ]
        }
    ],
    "version": "2.2.0"
}