{
    "asset": {
        "format": "png",
        "id": "c53cf559a4c28d7b168ff46eb5661ea3",
        "name": "1651947085.06.png",
        "path": "file:E:/Robocup/robocup/ml_data/victims/victims/1651947085.06.png",
        "size": {
            "width": 160,
            "height": 120
        },
        "state": 2,
        "type": 1
    },
    "regions": [
        {
            "id": "lmD_11FVi",
            "type": "RECTANGLE",
            "tags": [
                "dead"
            ],
            "boundingBox": {
                "height": 19.87012987012987,
                "width": 21.558441558441558,
                "left": 19.415584415584412,
                "top": 27.27272727272727
            },
            "points": [
                {
                    "x": 19.415584415584412,
                    "y": 27.27272727272727
                },
                {
                    "x": 40.97402597402597,
                    "y": 27.27272727272727
                },
                {
                    "x": 40.97402597402597,
                    "y": 47.14285714285714
                },
                {
                    "x": 19.415584415584412,
                    "y": 47.14285714285714
                }
            ]
        }
    ],
    "version": "2.2.0"
}