{
    "asset": {
        "format": "png",
        "id": "ca2ba00a56ba1101a385fad79d2cb15c",
        "name": "1651965820.4072812.png",
        "path": "file:E:/Robocup/robocup/ml_data/victims/victims/1651965820.4072812.png",
        "size": {
            "width": 160,
            "height": 120
        },
        "state": 2,
        "type": 1
    },
    "regions": [
        {
            "id": "bhbKI-KkN",
            "type": "RECTANGLE",
            "tags": [
                "living"
            ],
            "boundingBox": {
                "height": 38.831168831168824,
                "width": 38.31168831168831,
                "left": 79.54545454545453,
                "top": 65.45454545454545
            },
            "points": [
                {
                    "x": 79.54545454545453,
                    "y": 65.45454545454545
                },
                {
                    "x": 117.85714285714285,
                    "y": 65.45454545454545
                },
                {
                    "x": 117.85714285714285,
                    "y": 104.28571428571428
                },
                {
                    "x": 79.54545454545453,
                    "y": 104.28571428571428
                }
            ]
        }
    ],
    "version": "2.2.0"
}