{
    "asset": {
        "format": "png",
        "id": "dfe3e2c90757918ee8e1f8ce8841c87c",
        "name": "1651947137.63.png",
        "path": "file:E:/Robocup/robocup/ml_data/victims/victims/1651947137.63.png",
        "size": {
            "width": 160,
            "height": 120
        },
        "state": 2,
        "type": 1
    },
    "regions": [
        {
            "id": "4cqfsl7aF",
            "type": "RECTANGLE",
            "tags": [
                "living"
            ],
            "boundingBox": {
                "height": 20.129870129870127,
                "width": 20.389610389610386,
                "left": 10.584415584415584,
                "top": 34.54545454545454
            },
            "points": [
                {
                    "x": 10.584415584415584,
                    "y": 34.54545454545454
                },
                {
                    "x": 30.97402597402597,
                    "y": 34.54545454545454
                },
                {
                    "x": 30.97402597402597,
                    "y": 54.67532467532467
                },
                {
                    "x": 10.584415584415584,
                    "y": 54.67532467532467
                }
            ]
        }
    ],
    "version": "2.2.0"
}