{
    "asset": {
        "format": "png",
        "id": "e944d262fd764d0a8f9dd3046f4b2ce2",
        "name": "1651946600.0476136.png",
        "path": "file:E:/Robocup/robocup/ml_data/victims/victims/1651946600.0476136.png",
        "size": {
            "width": 160,
            "height": 120
        },
        "state": 2,
        "type": 1
    },
    "regions": [
        {
            "id": "OY-bFC6GN",
            "type": "RECTANGLE",
            "tags": [
                "living"
            ],
            "boundingBox": {
                "height": 28.701298701298697,
                "width": 28.96103896103896,
                "left": 66.42857142857142,
                "top": 43.246753246753244
            },
            "points": [
                {
                    "x": 66.42857142857142,
                    "y": 43.246753246753244
                },
                {
                    "x": 95.38961038961038,
                    "y": 43.246753246753244
                },
                {
                    "x": 95.38961038961038,
                    "y": 71.94805194805194
                },
                {
                    "x": 66.42857142857142,
                    "y": 71.94805194805194
                }
            ]
        }
    ],
    "version": "2.2.0"
}