{
    "asset": {
        "format": "png",
        "id": "f58987013bfbb7040c914571dceec53c",
        "name": "1651959624.8255527.png",
        "path": "file:E:/Robocup/robocup/ml_data/victims/victims/1651959624.8255527.png",
        "size": {
            "width": 160,
            "height": 120
        },
        "state": 2,
        "type": 1
    },
    "regions": [
        {
            "id": "FmIOb67wW",
            "type": "RECTANGLE",
            "tags": [
                "living"
            ],
            "boundingBox": {
                "height": 16.1038961038961,
                "width": 15.844155844155843,
                "left": 8.116883116883116,
                "top": 13.766233766233764
            },
            "points": [
                {
                    "x": 8.116883116883116,
                    "y": 13.766233766233764
                },
                {
                    "x": 23.96103896103896,
                    "y": 13.766233766233764
                },
                {
                    "x": 23.96103896103896,
                    "y": 29.87012987012987
                },
                {
                    "x": 8.116883116883116,
                    "y": 29.87012987012987
                }
            ]
        }
    ],
    "version": "2.2.0"
}